gdrive_client.py
py_gdrive_cli-0.0.2.dist-info/METADATA
py_gdrive_cli-0.0.2.dist-info/WHEEL
py_gdrive_cli-0.0.2.dist-info/entry_points.txt
py_gdrive_cli-0.0.2.dist-info/top_level.txt
py_gdrive_cli-0.0.2.dist-info/RECORD
