Metadata-Version: 2.2
Name: py-gdrive-cli
Version: 0.0.2
Summary: CLI tool to manage and interact with Google Drive Client API
Author-email: Tung Duong <duongthanhtungvn01@gmail.com>
License: Apache
Project-URL: homepage, https://github.com/dttvn0010/gdrive-cli
Requires-Python: >=3.8
Requires-Dist: google-api-python-client
Requires-Dist: google-auth-httplib2
Requires-Dist: google-auth-oauthlib
